setup.py
linkfinder/__init__.py
linkfinder/driver.py
linkfinder/main.py
linkfinder/runner.py
linkfinder/source.py
linkfinder.egg-info/PKG-INFO
linkfinder.egg-info/SOURCES.txt
linkfinder.egg-info/dependency_links.txt
linkfinder.egg-info/entry_points.txt
linkfinder.egg-info/requires.txt
linkfinder.egg-info/top_level.txt