Metadata-Version: 1.1
Name: linkfinder
Version: 0.0.1
Summary: Link Finder
Home-page: UNKNOWN
Author: Dan Nguyen
Author-email: dan.nguyens.mail@gmail.com
License: MIT
Keywords: links http gevent
Platform: UNKNOWN
Classifier: Development Status :: 3 - Alpha
